modypy/__init__.py
modypy/_version.py
modypy/linearization.py
modypy/simulation.py
modypy/steady_state.py
modypy/blocks/__init__.py
modypy/blocks/aerodyn.py
modypy/blocks/discont.py
modypy/blocks/discrete.py
modypy/blocks/elmech.py
modypy/blocks/linear.py
modypy/blocks/rigid.py
modypy/blocks/sources.py
modypy/model/__init__.py
modypy/model/events.py
modypy/model/ports.py
modypy/model/states.py
modypy/model/system.py
modypy/utils/__init__.py
modypy/utils/uiuc_db.py
modypy-3.0.0.dist-info/LICENSE
modypy-3.0.0.dist-info/METADATA
modypy-3.0.0.dist-info/WHEEL
modypy-3.0.0.dist-info/top_level.txt
modypy-3.0.0.dist-info/RECORD
