Metadata-Version: 2.1
Name: modypy
Version: 3.0.0
Summary: A framework for hierarchical modelling and simulation of dynamic systems
Home-page: https://modypy.org
Author: Ralf Gerlich
Author-email: ralf@ralfgerlich.biz
License: BSD 2-clause "Simplified" License
Platform: UNKNOWN
Classifier: Programming Language :: Python :: 3.6
Classifier: Programming Language :: Python :: 3.7
Classifier: Programming Language :: Python :: 3.8
Classifier: Programming Language :: Python :: 3.9
Classifier: License :: OSI Approved :: BSD License
Classifier: Operating System :: OS Independent
Classifier: Development Status :: 3 - Alpha
Classifier: Intended Audience :: Education
Classifier: Intended Audience :: Science/Research
Classifier: Topic :: Scientific/Engineering :: Physics
Classifier: Topic :: Scientific/Engineering :: Mathematics
Requires-Python: >=3.6
License-File: LICENSE
Requires-Dist: numpy (>=1.18.1)
Requires-Dist: scipy (>=1.5.4)
